fstree.cpython-311-x86_64-linux-musl.so
pyfstree.libs/libgcc_s-0cd532bd.so.1
pyfstree.libs/libstdc++-5d72f927.so.6.0.33
pyfstree-0.1.0.dist-info/METADATA
pyfstree-0.1.0.dist-info/WHEEL
pyfstree-0.1.0.dist-info/top_level.txt
pyfstree-0.1.0.dist-info/RECORD
pyfstree-0.1.0.dist-info/licenses/LICENSE
pyfstree-0.1.0.dist-info/sboms/auditwheel.cdx.json
