Metadata-Version: 2.4
Name: pyfstree
Version: 0.1.0
Summary: Python bindings for fstree - filesystem tree sharing and sync
Author: Robert Andersson
Author-email: Robert Andersson <rbrtandersson@gmail.com>
License: GPL-3.0-or-later
Project-URL: Homepage, https://github.com/srand/fstree
Project-URL: Repository, https://github.com/srand/fstree.git
Project-URL: Issues, https://github.com/srand/fstree/issues
Keywords: filesystem,sync,tree,fstree,merkle
Classifier: Development Status :: 3 - Alpha
Classifier: Intended Audience :: Developers
Classifier: Operating System :: OS Independent
Classifier: Programming Language :: Python :: 3
Classifier: Programming Language :: Python :: 3.7
Classifier: Programming Language :: Python :: 3.8
Classifier: Programming Language :: Python :: 3.9
Classifier: Programming Language :: Python :: 3.10
Classifier: Programming Language :: Python :: 3.11
Classifier: Programming Language :: Python :: 3.12
Classifier: Programming Language :: C++
Classifier: Topic :: Software Development :: Libraries :: Python Modules
Classifier: Topic :: System :: Filesystems
Classifier: Topic :: System :: Networking
Requires-Python: >=3.7
License-File: LICENSE
Requires-Dist: pybind11
Dynamic: author
Dynamic: license-file
Dynamic: requires-python
